r2c/__init__.py
r2c/cli/__init__.py
r2c/cli/__main__.py
r2c/cli/commands/__init__.py
r2c/cli/commands/build.py
r2c/cli/commands/cli.py
r2c/cli/commands/init.py
r2c/cli/commands/login.py
r2c/cli/commands/push.py
r2c/cli/commands/run.py
r2c/cli/commands/test.py
r2c/cli/commands/upload_inputset.py
r2c/cli/create_template.py
r2c/cli/errors.py
r2c/cli/logger.py
r2c/cli/network.py
r2c/cli/run.py
r2c/cli/util.py
r2c_cli-0.0.24.dist-info/entry_points.txt
r2c_cli-0.0.24.dist-info/LICENSE
r2c_cli-0.0.24.dist-info/WHEEL
r2c_cli-0.0.24.dist-info/METADATA
r2c_cli-0.0.24.dist-info/RECORD
