Metadata-Version: 2.1
Name: r2c-cli
Version: 0.0.24
Summary: A CLI for R2C
Home-page: https://ret2.co
Author: R2C
Author-email: cli@ret2.co
Requires-Python: >=3.6,<4.0
Classifier: License :: Other/Proprietary License
Classifier: Operating System :: OS Independent
Classifier: Programming Language :: Python :: 3
Classifier: Programming Language :: Python :: 3.6
Classifier: Programming Language :: Python :: 3.7
Classifier: Programming Language :: Python :: 3.8
Requires-Dist: click (>=7.0,<8.0)
Requires-Dist: docker (>=3.7,<4.0)
Requires-Dist: jsondiff (>=1.1,<2.0)
Requires-Dist: r2c-lib (>=0.0.19b2,<0.0.20)
Requires-Dist: requests (>=2.0,<3.0)
Requires-Dist: semantic-version (>=2.6,<3.0)
